nonebot_plugin_hammer_maij-2.1.0.dist-info/METADATA
nonebot_plugin_hammer_maij-2.1.0.dist-info/WHEEL
nonebot_plugin_hammer_maij-2.1.0.dist-info/licenses/LICENSE
nonebot_plugin_hammer_maij/__init__.py
nonebot_plugin_hammer_maij/config.py
nonebot_plugin_hammer_maij/group_mapping.py
nonebot_plugin_hammer_maij/handler/__init__.py
nonebot_plugin_hammer_maij/handler/admin_handler.py
nonebot_plugin_hammer_maij/handler/alias_handler.py
nonebot_plugin_hammer_maij/handler/announcement_handler.py
nonebot_plugin_hammer_maij/handler/city_handler.py
nonebot_plugin_hammer_maij/handler/handle_utils.py
nonebot_plugin_hammer_maij/handler/log_handler.py
nonebot_plugin_hammer_maij/handler/place_handler.py
nonebot_plugin_hammer_maij/handler/statistics_handler.py
nonebot_plugin_hammer_maij/http/__init__.py
nonebot_plugin_hammer_maij/http/http_client.py
nonebot_plugin_hammer_maij/http/http_models.py
nonebot_plugin_hammer_maij/http/http_utils.py
nonebot_plugin_hammer_maij/http/response_exception.py
nonebot_plugin_hammer_maij/time_utils.py
nonebot_plugin_hammer_maij-2.1.0.dist-info/RECORD
