Metadata-Version: 2.1
Name: nonebot-plugin-hammer-maij
Version: 2.1.0
Summary: A Nonebot2 plugin implements MaiJ API 3.0, which helps MaimaiDX players share the information of game zones.
Author-Email: ArgonarioD <argonariod@outlook.com>
License: Apache-2.0
Requires-Python: >=3.9
Requires-Dist: nonebot2>=2.1.0
Requires-Dist: nonebot-adapter-onebot>=2.3.0
Requires-Dist: nonebot-plugin-localstore>=0.5.0
Requires-Dist: httpx[http2]>=0.26.0
Requires-Dist: nonebot-plugin-hammer-core>=0.3.3
Requires-Dist: playwright>=1.41.0
